pfctl_exporter.py
pfctl_exporter-0.5.1.dist-info/LICENSE
pfctl_exporter-0.5.1.dist-info/METADATA
pfctl_exporter-0.5.1.dist-info/WHEEL
pfctl_exporter-0.5.1.dist-info/entry_points.txt
pfctl_exporter-0.5.1.dist-info/top_level.txt
pfctl_exporter-0.5.1.dist-info/RECORD
